{
    "array": [
        {
            "name": "Person",
            "sentence": "Hi mom! It's me!"
        },
        {
            "name": "Person",
            "sentence": "I'll call you back later, or call me whenever you get this."
        },
        {
            "name": "Person",
            "sentence": "I just could not wait to tell you..."
        },
        {
            "name": "Person",
            "sentence": "... It worked!"
        },
        {
            "name": "Person",
            "sentence": "The surgery took about an hour only, and they let me out of the clinic tonight."
        },
        {
            "name": "Person",
            "sentence": "I'll just have to go for a control appointment in a week."
        },
        {
            "name": "Person",
            "sentence": "I'm still a bit tired but I can not believe my eyes."
        },
        {
            "name": "Person",
            "sentence": "I can see, mom!"
        },
        {
            "name": "Person",
            "sentence": "The lights, the city ... Everything is so beautiful."
        },
        {
            "name": "Person",
            "sentence": "I've been staring at it for almost an hour now."
        },
        {
            "name": "Person",
            "sentence": "It's like discovering life all over again!"
        },
        {
            "name": "Person",
            "sentence": "Doctor Van Der Waals took care of all the costs, he said money should not be a condition for curing unfair disabilities."
        },
        {
            "name": "Person",
            "sentence": "Can you believe that we'll finally be able to go to art shows, cook, watch TV together?"
        },
        {
            "name": "Person",
            "sentence": "It feels like a dream come true, mom!"
        },
        {
            "name": "Person",
            "sentence": "*sighs*"
        },
        {
            "name": "Person",
            "sentence": "I guess you and dad must be asleep by now, I'll see you two tomorrow."
        },
        {
            "name": "Person",
            "sentence": "I-I'll ... See... You two, tomorrow haha!"
        },
        {
            "name": "Person",
            "sentence": "I can't wait to see your faces for the first time."
        }
    ]
}